MANIFEST.in
README.rst
Readme.rst
setup.py
cabric/__init__.py
cabric/__init__.pyc
cabric/api.py
cabric/api.pyc
cabric/bridge.py
cabric/bridge.pyc
cabric/env.py
cabric/env.pyc
cabric/hack.py
cabric/hack.pyc
cabric/main.py
cabric/utils.py
cabric/utils.pyc
cabric.egg-info/PKG-INFO
cabric.egg-info/SOURCES.txt
cabric.egg-info/dependency_links.txt
cabric.egg-info/entry_points.txt
cabric.egg-info/requires.txt
cabric.egg-info/top_level.txt
cabric/__pycache__/__init__.cpython-35.pyc
cabric/__pycache__/__init__.cpython-36.pyc
cabric/__pycache__/__init__.pypy3-59.pyc
cabric/__pycache__/bridge.cpython-35.pyc
cabric/__pycache__/bridge.cpython-36.pyc
cabric/__pycache__/main.cpython-35.pyc
cabric/__pycache__/main.cpython-36.pyc
cabric/__pycache__/main.pypy3-59.pyc
cabric/__pycache__/utils.cpython-35.pyc
cabric/__pycache__/utils.cpython-36.pyc
cabric/__pycache__/utils.pypy3-59.pyc
cabric/cloud/__init__.py
cabric/cloud/__init__.pyc
cabric/cloud/qingcloud.py
cabric/cloud/qingcloud.pyc
cabric/components/__init__.py
cabric/components/__init__.pyc
cabric/components/check.py
cabric/components/clean.py
cabric/components/compile.py
cabric/components/compose.py
cabric/components/compose.pyc
cabric/components/config.py
cabric/components/config.pyc
cabric/components/deploy.py
cabric/components/deploy.pyc
cabric/components/hardline.py
cabric/components/hardline.pyc
cabric/components/install.py
cabric/components/install.pyc
cabric/components/mini.py
cabric/components/mini.pyc
cabric/components/package.py
cabric/components/render.py
cabric/components/render.pyc
cabric/components/touch.py
cabric/components/touch.pyc
cabric/components/update.py
cabric/components/update.pyc
cabric/components/__pycache__/__init__.cpython-35.pyc
cabric/components/__pycache__/__init__.cpython-36.pyc
cabric/components/__pycache__/__init__.pypy3-59.pyc
cabric/components/__pycache__/check.pypy3-59.pyc
cabric/components/__pycache__/compose.cpython-35.pyc
cabric/components/__pycache__/deploy.cpython-36.pyc
cabric/components/__pycache__/hardline.cpython-36.pyc
cabric/dns/__init__.py
cabric/dns/__init__.pyc
cabric/dns/dnspod.py
cabric/dns/dnspod.pyc
tests/cloud/__init__.py
tests/cloud/qingcloud.py
