Metadata-Version: 1.1
Name: cabric
Version: 1.0.9
Summary: Cabric,a deploy tool for CentOS,based on Fabric.
Home-page: https://github.com/nextoa/cabric
Author: WANG WENPEI
Author-email: wangwenpei@nextoa.com
License: http://opensource.org/licenses/MIT
Download-URL: https://github.com/nextoa/cabric/tarball/master
Keywords: fabric,cabric
Platform: UNKNOWN
